setup.cfg
setup.py
arrowlogistics/ArrowsLogisticsCore.py
arrowlogistics/_init_.py
arrowlogistics.egg-info/PKG-INFO
arrowlogistics.egg-info/SOURCES.txt
arrowlogistics.egg-info/dependency_links.txt
arrowlogistics.egg-info/not-zip-safe
arrowlogistics.egg-info/top_level.txt