Metadata-Version: 2.1
Name: arrowlogistics
Version: 0.4
Summary: ArrowLogics
Author-email: zxctails@gmail.com
